dwell/__init__.py
dwell/single_phase_non_isothermal/add_bc_extra_nodes.py
dwell/single_phase_non_isothermal/add_bc_nodes.py
dwell/single_phase_non_isothermal/add_bc_sources_sinks.py
dwell/single_phase_non_isothermal/assemble_primary_variables_list.py
dwell/single_phase_non_isothermal/define_fluid_model.py
dwell/single_phase_non_isothermal/define_pipe_geometry.py
dwell/single_phase_non_isothermal/generate_rampup_time_steps.py
dwell/single_phase_non_isothermal/pipe_model.py
dwell/single_phase_non_isothermal/save_results.py
dwell/single_phase_non_isothermal/set_initial_conditions.py
dwell/single_phase_non_isothermal/simulate.py
dwell/two_phase/add_bc_extra_nodes.py
dwell/two_phase/add_bc_nodes.py
dwell/two_phase/add_bc_sources_sinks.py
dwell/two_phase/assemble_primary_variables_list.py
dwell/two_phase/calc_rough_K_value.py
dwell/two_phase/check_initial_conditions.py
dwell/two_phase/define_fluid_model.py
dwell/two_phase/define_pipe_geometry.py
dwell/two_phase/generate_rampup_time_steps.py
dwell/two_phase/pipe_model.py
dwell/two_phase/save_results.py
dwell/two_phase/set_initial_conditions.py
dwell/two_phase/set_initial_conditions_wh_at_centroid.py
dwell/two_phase/simulate.py
dwell/utilities/library.py
dwell/utilities/units.py
open_dwell-0.1.2.dist-info/licenses/LICENSE
open_dwell-0.1.2.dist-info/METADATA
open_dwell-0.1.2.dist-info/WHEEL
open_dwell-0.1.2.dist-info/entry_points.txt
open_dwell-0.1.2.dist-info/top_level.txt
open_dwell-0.1.2.dist-info/RECORD
