Metadata-Version: 2.4
Name: open-dwell
Version: 0.1.2
Summary: A stand alone wellbore simulator for energy transition applications.
Author-email: Sajjad Moslehi <s.moslehi@tudelft.nl>
License: Apache-2.0
Project-URL: Homepage, https://darts.citg.tudelft.nl/members.html
Project-URL: Repository, https://gitlab.com/open-darts/dwell
Keywords: energy transition,subsurface CO2 sequestration,geothermal energy extraction,underground hydrogen storage
Classifier: Development Status :: 3 - Alpha
Classifier: License :: OSI Approved :: Apache Software License
Classifier: Programming Language :: Python :: 3
Classifier: Intended Audience :: Science/Research
Classifier: Topic :: Scientific/Engineering :: Physics
Classifier: Topic :: Software Development :: Libraries :: Python Modules
Requires-Python: >=3.8
License-File: LICENSE
Requires-Dist: numpy
Requires-Dist: pandas
Requires-Dist: scipy
Requires-Dist: numba
Requires-Dist: open-darts-flash
Dynamic: license-file
